twidi/__init__.py
twidi/__main__.py
twidi/admin/__init__.py
twidi/admin/bot.py
twidi/admin/config.py
twidi/admin/data/redemptions.json
twidi/admin/data.py
twidi/admin/main.py
twidi/admin/models.py
twidi/admin/static/layout.css
twidi/admin/templates/bot.html
twidi/admin/templates/debug.html
twidi/admin/templates/layout.html
twidi/admin/templates/message_edit.html
twidi/admin/templates/message_tester.html
twidi/admin/templates/redemptions.html
twidi/admin/v0.0.0_Twidi.sqlite
twidi/admin/views/bot.py
twidi/admin/views/debug.py
twidi/admin/views/message.py
twidi/admin/views/redemptions.py
twidi/device/__init__.py
twidi/device/devices.py
twidi/logger/__init__.py
twidi/logger/logger.py
twidi/twitch/__init__.py
twidi/twitch/midi_bot.py
twidi/twitch/pub_sub_client.py
twidi-0.0.19.dev0.dist-info/entry_points.txt
twidi-0.0.19.dev0.dist-info/WHEEL
twidi-0.0.19.dev0.dist-info/METADATA
twidi-0.0.19.dev0.dist-info/RECORD
