Metadata-Version: 2.1
Name: twidi
Version: 0.0.19.dev0
Summary: Creates a simple bridge between Twitch chat commands and MIDI controls
Author: Greg Hatt
Author-email: ghattjr@gmail.com
Requires-Python: >=3.8,<4.0
Classifier: Programming Language :: Python :: 3
Classifier: Programming Language :: Python :: 3.10
Classifier: Programming Language :: Python :: 3.8
Classifier: Programming Language :: Python :: 3.9
Requires-Dist: Flask-Admin (>=1.5.8,<2.0.0)
Requires-Dist: Flask-DebugToolbar (>=0.11.0,<0.12.0)
Requires-Dist: Flask-SQLAlchemy (>=2.5.1,<3.0.0)
Requires-Dist: PyYAML (>=6.0,<7.0)
Requires-Dist: SQLAlchemy (>=1.4.31,<2.0.0)
Requires-Dist: SQLAlchemy-Utils (>=0.38.2,<0.39.0)
Requires-Dist: black (>=21.12b0,<22.0)
Requires-Dist: cleo (>=0.8.1,<0.9.0)
Requires-Dist: fire (>=0.4.0,<0.5.0)
Requires-Dist: mido (>=1.2.10,<2.0.0)
Requires-Dist: pygame (>=2.1.2,<3.0.0)
Requires-Dist: pytest (>=6.2.5,<7.0.0)
Requires-Dist: twitchio (>=2.1.4,<3.0.0)
Requires-Dist: yamlable (>=1.0.4,<2.0.0)
